odoo/addons/beesdoo_shift_welcome_screen/README.rst
odoo/addons/beesdoo_shift_welcome_screen/__init__.py
odoo/addons/beesdoo_shift_welcome_screen/__manifest__.py
odoo/addons/beesdoo_shift_welcome_screen/i18n/beesdoo_shift_welcome_screen.pot
odoo/addons/beesdoo_shift_welcome_screen/models/__init__.py
odoo/addons/beesdoo_shift_welcome_screen/models/welcome.py
odoo/addons/beesdoo_shift_welcome_screen/readme/CONTRIBUTORS.rst
odoo/addons/beesdoo_shift_welcome_screen/readme/DESCRIPTION.rst
odoo/addons/beesdoo_shift_welcome_screen/static/description/index.html
odoo/addons/beesdoo_shift_welcome_screen/views/welcome.xml
odoo12_addon_beesdoo_shift_welcome_screen-12.0.1.0.1.99.dev9.dist-info/METADATA
odoo12_addon_beesdoo_shift_welcome_screen-12.0.1.0.1.99.dev9.dist-info/WHEEL
odoo12_addon_beesdoo_shift_welcome_screen-12.0.1.0.1.99.dev9.dist-info/top_level.txt
odoo12_addon_beesdoo_shift_welcome_screen-12.0.1.0.1.99.dev9.dist-info/RECORD
