Metadata-Version: 2.1
Name: odoo12-addon-beesdoo-shift-welcome-screen
Version: 12.0.1.0.1.99.dev9
Summary: Volunteer Timetable Management
Home-page: https://github.com/beescoop/Obeesdoo
Author: Thibault Francois, Coop IT Easy SC
License: AGPL-3
Platform: UNKNOWN
Classifier: Programming Language :: Python
Classifier: Framework :: Odoo
Classifier: Framework :: Odoo :: 12.0
Classifier: License :: OSI Approved :: GNU Affero General Public License v3
Requires-Python: >=3.5
Requires-Dist: odoo12-addon-beesdoo-shift
Requires-Dist: odoo (<12.1dev,>=12.0a)
